omdctk/__init__.py
omdctk/check_fastqs.py
omdctk/check_metadata_ENA.py
omdctk/check_metadata_values.py
omdctk/concat_datasets.py
omdctk/download_fastqs.py
omdctk/download_metadata_ENA.py
omdctk/filter_metadata.py
omdctk/make_treatment_template.py
omdctk/merge_metadata.py
omdctk/omdctk_common.py
omdctk/test_omdctk.py
omdctk/treat_fastqs.py
omdctk/treat_metadata.py
omdctk/test_info/CRA001372_check_fastqs_Generic_reference.log
omdctk/test_info/CRA001372_filterfile_example.tsv
omdctk/test_info/CRA001372_main_metadata_example.tsv
omdctk/test_info/CRA001372_publication_metadata_example.tsv
omdctk/test_info/PRJEB10949_check_fastqs_ENA_reference.log
omdctk/test_info/PRJEB10949_check_metadata_ENA_reference.log
omdctk/test_info/PRJEB10949_filterfile_example.tsv
omdctk/test_info/PRJEB10949_publication_example.tsv
omdctk/test_info/check_metadata_values_example_reference.log
omdctk/test_info/curated_CRA001372_external_example_metadata_final.tsv
omdctk/test_info/curated_PRJEB10949_ENA_example_metadata_final.tsv
omdctk/test_info/filtered_CRA001372_URLS_example.txt
omdctk/test_info/filtered_manifest_CRA001372_example.tsv
omdctk/test_info/treatment_template_filtered_CRA001372_example.tsv
omdctk/test_info/treatment_template_filtered_PRJEB10949_merged_metadata_example.tsv
omdctk/test_info/variables_dictionary_example.tsv
omdctk-1.1.0.dist-info/LICENSE
omdctk-1.1.0.dist-info/METADATA
omdctk-1.1.0.dist-info/WHEEL
omdctk-1.1.0.dist-info/entry_points.txt
omdctk-1.1.0.dist-info/top_level.txt
omdctk-1.1.0.dist-info/RECORD
