Metadata-Version: 2.1
Name: omdctk
Version: 1.1.0
Summary: OMD Curation Toolkit
Author-email: Samuel Piquer Esteban <samuel.piquer@uv.es>
Project-URL: GitHub, https://github.com/tbcgit/omdctk
Project-URL: Documentation, https://github.com/tbcgit/omdctk/wiki
Classifier: Programming Language :: Python :: 3
Classifier: License :: OSI Approved :: MIT License
Classifier: Operating System :: OS Independent
Classifier: Intended Audience :: Science/Research
Classifier: Topic :: Scientific/Engineering :: Bio-Informatics
Requires-Python: >=3.10
License-File: LICENSE
Requires-Dist: aioftp
Requires-Dist: aiohttp
Requires-Dist: parfive
Requires-Dist: termcolor
Requires-Dist: tabulate
Requires-Dist: tqdm
Requires-Dist: mg-toolkit
Requires-Dist: pandas
